Metadata-Version: 2.1
Name: istart
Version: 0.0.1
Summary: Kick start data science package
Home-page: https://github.com/atulyanarayan/istart
Author: Atulya Narayan
Author-email: atulya.iims@gmail.com
License: UNKNOWN
Platform: UNKNOWN
Classifier: Programming Language :: Python :: 3
Classifier: License :: OSI Approved :: MIT License
Classifier: Operating System :: OS Independent
